leonhard/__init__.py
leonhard/helpers.py
leonhard/leonhard.py
tests/__init__.py
tests/test_helpers.py
tests/test_leonhard.py
leonhard-1.6.5.dist-info/LICENSE
leonhard-1.6.5.dist-info/METADATA
leonhard-1.6.5.dist-info/WHEEL
leonhard-1.6.5.dist-info/top_level.txt
leonhard-1.6.5.dist-info/RECORD
