Metadata-Version: 2.1
Name: leonhard
Version: 1.6.5
Summary: A commons library for Project Euler problems.
Home-page: https://github.com/migzpogi/leonhard
Author: Migz Estrella
Author-email: me@migzestrella.com
License: UNKNOWN
Platform: UNKNOWN
Classifier: Programming Language :: Python :: 3
Classifier: License :: OSI Approved :: MIT License
Classifier: Operating System :: OS Independent
Requires-Python: >=3.6
License-File: LICENSE
